ourskyai_astro_api/__init__.py
ourskyai_astro_api/api_client.py
ourskyai_astro_api/api_response.py
ourskyai_astro_api/configuration.py
ourskyai_astro_api/exceptions.py
ourskyai_astro_api/py.typed
ourskyai_astro_api/rest.py
ourskyai_astro_api/api/__init__.py
ourskyai_astro_api/api/default_api.py
ourskyai_astro_api/models/__init__.py
ourskyai_astro_api/models/asset_file_type.py
ourskyai_astro_api/models/asset_type.py
ourskyai_astro_api/models/calibration_master_type.py
ourskyai_astro_api/models/daily_weather_city.py
ourskyai_astro_api/models/daily_weather_forecast_item.py
ourskyai_astro_api/models/daily_weather_forecast_item_temp.py
ourskyai_astro_api/models/daily_weather_forecast_item_weather_inner.py
ourskyai_astro_api/models/daily_weather_forecast_list_response.py
ourskyai_astro_api/models/empty_success.py
ourskyai_astro_api/models/filter_type.py
ourskyai_astro_api/models/fits_header.py
ourskyai_astro_api/models/image_set_type.py
ourskyai_astro_api/models/integration_time.py
ourskyai_astro_api/models/location.py
ourskyai_astro_api/models/mount_type.py
ourskyai_astro_api/models/node_state.py
ourskyai_astro_api/models/optical_tube_type.py
ourskyai_astro_api/models/shutter_type.py
ourskyai_astro_api/models/successful_create.py
ourskyai_astro_api/models/tracking_type.py
ourskyai_astro_api/models/v1_astro_project.py
ourskyai_astro_api/models/v1_astro_project_asset.py
ourskyai_astro_api/models/v1_astro_project_asset_metadata.py
ourskyai_astro_api/models/v1_astro_project_asset_metadata_color_combination.py
ourskyai_astro_api/models/v1_astro_target.py
ourskyai_astro_api/models/v1_calibration_master.py
ourskyai_astro_api/models/v1_camera.py
ourskyai_astro_api/models/v1_create_astro_project_image_set_request.py
ourskyai_astro_api/models/v1_create_astro_project_request.py
ourskyai_astro_api/models/v1_create_astro_project_response.py
ourskyai_astro_api/models/v1_create_calibration_master_request.py
ourskyai_astro_api/models/v1_create_calibration_master_response.py
ourskyai_astro_api-1.3.9356.dist-info/METADATA
ourskyai_astro_api-1.3.9356.dist-info/WHEEL
ourskyai_astro_api-1.3.9356.dist-info/top_level.txt
ourskyai_astro_api-1.3.9356.dist-info/RECORD
